baseline/Baseline1 (k-annonymity).py
baseline/Baseline2.py
baseline/Baseline3.py
baseline/__init__.py
baseline/test_baseline_2.py
p_tlkc_privacy/Anonymizer.py
p_tlkc_privacy/ELRepresentation.py
p_tlkc_privacy/MFS.py
p_tlkc_privacy/MVS.py
p_tlkc_privacy/__init__.py
p_tlkc_privacy/privacyPreserving.py
p_tlkc_privacy/results.py
p_tlkc_privacy-0.0.14.dist-info/LICENSE
p_tlkc_privacy-0.0.14.dist-info/METADATA
p_tlkc_privacy-0.0.14.dist-info/WHEEL
p_tlkc_privacy-0.0.14.dist-info/pbr.json
p_tlkc_privacy-0.0.14.dist-info/top_level.txt
p_tlkc_privacy-0.0.14.dist-info/RECORD
