Metadata-Version: 2.1
Name: p-tlkc-privacy
Version: 0.0.14
Summary: TLKC-privacy model for process mining
Home-page: https://github.com/m4jidRafiei/TLKC-Privacy
Author: Majid Rafiei
Author-email: majid.rafiei@pads.rwth-aachen.de
License: UNKNOWN
Project-URL: Source, https://github.com/m4jidRafiei/TLKC-Privacy
Platform: UNKNOWN
Classifier: Programming Language :: Python :: 3
Classifier: License :: OSI Approved :: MIT License
Classifier: Operating System :: OS Independent
Requires-Dist: pm4py (==1.2.10)
Requires-Dist: typing (==3.6.4)
Requires-Dist: setuptools (==41.0.1)
Requires-Dist: mlxtend (==0.14.0)
Requires-Dist: pyfpgrowth (==1.0)
Requires-Dist: pandas (==0.24.2)
Requires-Dist: numpy (>=1.18.1)
Requires-Dist: p-privacy-metadata (==0.0.4)
